README.rst
setup.py
matterhook/__init__.py
matterhook/attachments.py
matterhook/incoming.py
matterhook.egg-info/PKG-INFO
matterhook.egg-info/SOURCES.txt
matterhook.egg-info/dependency_links.txt
matterhook.egg-info/top_level.txt
matterhook.egg-info/zip-safe