Metadata-Version: 1.1
Name: matterhook
Version: 0.2
Summary: Interact with Mattermost incoming webhooks easily.
Home-page: https://github.com/numberly/matterhook
Author: numberly
Author-email: UNKNOWN
License: BSD
Download-URL: https://github.com/numberly/matterhook/tags
Platform: any
Classifier: License :: OSI Approved :: BSD License
Classifier: Operating System :: POSIX :: Linux
Classifier: Programming Language :: Python
Classifier: Programming Language :: Python :: 3
Classifier: Programming Language :: Python :: 3.5
Classifier: Programming Language :: Python :: 3.6
Classifier: Programming Language :: Python :: 3.7
Classifier: Programming Language :: Python :: 3.8
Classifier: Programming Language :: Python :: 3.9
Classifier: Topic :: Software Development :: Libraries :: Python Modules
